examples/example1/policy_pipeline.py
examples/example1/setup.template.py
policy_tool/main.py
policy_tool/core/policy_assignment_types.py
policy_tool/core/snowflake_connection_setup.py
policy_tool/services/policy_assignment_comparison_service.py
policy_tool/services/policy_configuration_service.py
policy_tool/services/policy_metadata_service.py
policy_tool/services/policy_solution_service.py
policy_tool/services/policy_validation_service.py
policy_tool/services/snowflake_service.py
policy_tool/utils/file_utils.py
policy_tool/utils/logger_utils.py
policy_tool/utils/parallelization_util.py
resources/json-schemas/configs/configs.schema.json
resources/json-schemas/policy_assignments/column_masking_policies.schema.json
resources/json-schemas/policy_assignments/policy_assignments.schema.json
resources/json-schemas/policy_assignments/row_access_policies.schema.json
acepolicies-0.1.23.dist-info/METADATA
acepolicies-0.1.23.dist-info/WHEEL
acepolicies-0.1.23.dist-info/top_level.txt
acepolicies-0.1.23.dist-info/RECORD
